mdtl/__init__.py
mdtl-0.1.0.dist-info/METADATA
mdtl-0.1.0.dist-info/WHEEL
mdtl-0.1.0.dist-info/entry_points.txt
mdtl-0.1.0.dist-info/RECORD
