Metadata-Version: 2.1
Name: mdtl
Version: 0.1.0
Summary: Lint your markdown tables with CJK letters.
Author: Philip Fan
Author-email: topfyf@qq.com
Requires-Python: >=3.10,<4.0
Classifier: Programming Language :: Python :: 3
Classifier: Programming Language :: Python :: 3.10
Classifier: Programming Language :: Python :: 3.11
Classifier: Programming Language :: Python :: 3.12
